paper_ready/__init__.py
paper_ready/kitti_utils.py
paper_ready/lidar_benchmark.py
paper_ready/mri_deep_dive.py
paper_ready/mri_deep_dive_fast.py
paper_ready/pointcloud.py
paper_ready/pointcloud_benchmark.py
paper_ready/io/__init__.py
paper_ready/io/volume.py
paper_ready/methodology/__init__.py
paper_ready/methodology/selection.py
paper_ready/methodology/witness_ph.py
paper_ready/pipeline/__init__.py
paper_ready/pipeline/diagrams.py
paper_ready/pipeline/landmarks.py
paper_ready/pipeline/metrics.py
paper_ready/pipeline/reference.py
paper_ready/sampling/__init__.py
paper_ready/sampling/hybrid_sampler.py
paper_ready/tda_odometry/__init__.py
paper_ready/tda_odometry/evaluation.py
paper_ready/tda_odometry/features.py
paper_ready/tda_odometry/models.py
paper_ready/tda_odometry/training.py
whale/__init__.py
whale/ai.py
whale/pointcloud.py
whale/io/__init__.py
whale/io/volume.py
whale/methodology/__init__.py
whale/methodology/fast_landmarks.py
whale/methodology/selection.py
whale/methodology/witness_ph.py
whale/mri/__init__.py
whale/mri/deep_dive.py
whale/mri/deep_dive_fast.py
whale/pipeline/__init__.py
whale/pipeline/diagrams.py
whale/pipeline/landmarks.py
whale/pipeline/metrics.py
whale/pipeline/reference.py
whale/sampling/__init__.py
whale/sampling/hybrid_sampler.py
whale_tda-0.3.0.dist-info/licenses/LICENSE
whale_tda-0.3.0.dist-info/METADATA
whale_tda-0.3.0.dist-info/WHEEL
whale_tda-0.3.0.dist-info/entry_points.txt
whale_tda-0.3.0.dist-info/top_level.txt
whale_tda-0.3.0.dist-info/RECORD
