Metadata-Version: 2.4
Name: whale-tda
Version: 0.3.0
Summary: Fast landmark-based witness persistence for point clouds and volumetric data.
Author-email: Jorge Ruiz Williams <jorgeruizwilliams@gmail.com>
License-Expression: MIT
Project-URL: Homepage, https://github.com/JorgeLRW/whale
Project-URL: Documentation, https://github.com/JorgeLRW/whale#readme
Project-URL: Issues, https://github.com/JorgeLRW/whale/issues
Project-URL: Source, https://github.com/JorgeLRW/whale
Keywords: topological-data-analysis,persistent-homology,mri,landmarks
Classifier: Development Status :: 4 - Beta
Classifier: Intended Audience :: Science/Research
Classifier: Programming Language :: Python
Classifier: Programming Language :: Python :: 3
Classifier: Programming Language :: Python :: 3.10
Classifier: Programming Language :: Python :: 3.11
Classifier: Programming Language :: Python :: 3.12
Classifier: Topic :: Scientific/Engineering :: Medical Science Apps.
Classifier: Topic :: Scientific/Engineering :: Information Analysis
Requires-Python: >=3.9
License-File: LICENSE
Requires-Dist: numpy>=1.21
Requires-Dist: scipy>=1.8
Requires-Dist: scikit-learn>=1.0
Requires-Dist: nibabel>=5.0
Requires-Dist: numba>=0.57
Requires-Dist: hnswlib>=0.6
Requires-Dist: faiss-cpu>=1.7
Provides-Extra: dev
Requires-Dist: pytest; extra == "dev"
Requires-Dist: build; extra == "dev"
Requires-Dist: twine; extra == "dev"
Requires-Dist: pip-licenses; extra == "dev"
Provides-Extra: docs
Requires-Dist: mkdocs-material; extra == "docs"
Provides-Extra: ai
Requires-Dist: torch>=2.0; extra == "ai"
Provides-Extra: lidar
Requires-Dist: torch>=2.0; extra == "lidar"
Requires-Dist: tqdm>=4.60; extra == "lidar"
Provides-Extra: mapping
Requires-Dist: torch>=2.0; extra == "mapping"
Requires-Dist: tqdm>=4.60; extra == "mapping"
Dynamic: license-file
